<?xml version="1.0" encoding="UTF-8"?>
<objects serializationModel="Studio.02.00.00">
	<object class="AudioFile" id="{4cbd1e98-68b8-4253-9a7a-b8c03c0bdb20}">
		<property name="assetPath">
			<value>Conga Soft.aif</value>
		</property>
		<property name="frequencyInKHz">
			<value>44.0999985</value>
		</property>
		<property name="channelCount">
			<value>2</value>
		</property>
		<property name="length">
			<value>0.16707482993197278</value>
		</property>
		<relationship name="masterAssetFolder">
			<destination>{342d7785-552f-4999-9a9d-35eead1923e2}</destination>
		</relationship>
	</object>
</objects>
